MANIFEST.in
README.rst
setup.py
djlime_metatags.egg-info/PKG-INFO
djlime_metatags.egg-info/SOURCES.txt
djlime_metatags.egg-info/dependency_links.txt
djlime_metatags.egg-info/top_level.txt
metatags/__init__.py
metatags/admin.py
metatags/apps.py
metatags/decorators.py
metatags/forms.py
metatags/models.py
metatags/translation.py
metatags/utils.py
metatags/locale/ru/LC_MESSAGES/django.mo
metatags/locale/ru/LC_MESSAGES/django.po
metatags/locale/uk/LC_MESSAGES/django.mo
metatags/locale/uk/LC_MESSAGES/django.po
metatags/management/__init__.py
metatags/management/commands/__init__.py
metatags/management/commands/syncmetatags.py
metatags/migrations/0001_initial.py
metatags/migrations/__init__.py
metatags/south_migrations/0001_initial.py
metatags/south_migrations/__init__.py
metatags/static/css/meta_tags.css
metatags/templates/admin/metatags/metatag/change_form.html
metatags/templates/metatags/_meta_tags.html
metatags/templates/metatags/edit_inline/stacked.html
metatags/templatetags/__init__.py
metatags/templatetags/meta_tags.py
metatags/tests/__init__.py
metatags/tests/tests.py