Metadata-Version: 1.0
Name: djlime-metatags
Version: 0.9.11
Summary: Django application for attaching meta-tags to objects and
Home-page: https://github.com/whitespy/djlime-metatags
Author: Andrey Butenko
Author-email: whitespysoftware@yandex.ru
License: UNKNOWN
Platform: any
